setup.py
StringMethod/__init__.py
StringMethod/primsekstr.py
StringMethod.egg-info/PKG-INFO
StringMethod.egg-info/SOURCES.txt
StringMethod.egg-info/dependency_links.txt
StringMethod.egg-info/top_level.txt