Metadata-Version: 2.1
Name: StringMethod
Version: 0.2.5
Summary: A library that stores operations on strings
Home-page: https://github.com/
Author: haowen zhang
Author-email: 806670753@qq.com
License: UNKNOWN
Platform: UNKNOWN
Classifier: Programming Language :: Python :: 3
Classifier: License :: OSI Approved :: MIT License
Classifier: Operating System :: OS Independent
